howlermonkey/__init__.py
howlermonkey/client.py
howlermonkey/server.py
howlermonkey-1.0.2.dist-info/DESCRIPTION.rst
howlermonkey-1.0.2.dist-info/METADATA
howlermonkey-1.0.2.dist-info/RECORD
howlermonkey-1.0.2.dist-info/WHEEL
howlermonkey-1.0.2.dist-info/metadata.json
howlermonkey-1.0.2.dist-info/top_level.txt
