Metadata-Version: 2.0
Name: howlermonkey
Version: 1.0.2
Summary: A slack messaging authentication andinterfacing system for the DTG
Home-page: https://gitlab.dtg.cl.cam.ac.uk/infrastructure/howler-monkey/
Author: Thomas Bytheway
Author-email: thomas.bytheway@cl.cam.ac.uk
License: MIT
Platform: UNKNOWN
Classifier: Development Status :: 3 - Alpha
Classifier: License :: OSI Approved :: MIT License
Classifier: Programming Language :: Python :: 3
Classifier: Programming Language :: Python :: 3.5
Requires-Dist: pyyaml (>=3.11)
Requires-Dist: requests (>=2.10.0)
